MANIFEST.in
README.md
setup.py
diana/__init__.py
diana/encoding.py
diana/enumerations.py
diana/object_update.py
diana/packet.py
diana/socket.py
diana/tracking.py
diana/utils/__init__.py
diana/utils/proxy.py
diana/utils/stream.py
libdiana.egg-info/PKG-INFO
libdiana.egg-info/SOURCES.txt
libdiana.egg-info/dependency_links.txt
libdiana.egg-info/top_level.txt
libdiana.egg-info/zip-safe