Metadata-Version: 1.0
Name: libdiana
Version: 0.0.6
Summary: Library for talking to Artemis SBS.
Home-page: https://github.com/prophile/libdiana
Author: Alistair Lynn
Author-email: arplynn@gmail.com
License: MIT
Platform: UNKNOWN
